bpe_openai-0.1.4.dist-info/METADATA
bpe_openai-0.1.4.dist-info/WHEEL
bpe_openai/__init__.py
bpe_openai/_bindings.abi3.so
bpe_openai/_bindings.pyi
bpe_openai/compat.py
bpe_openai/configuration.py
bpe_openai/data/__init__.py
bpe_openai/data/cl100k_base.tiktoken.gz
bpe_openai/data/o200k_base.tiktoken.gz
bpe_openai/data/voyage3_base.tiktoken.gz
bpe_openai/errors.py
bpe_openai/metrics.py
bpe_openai/registry.py
bpe_openai/results.py
bpe_openai/tokenizer.py
bpe_openai-0.1.4.dist-info/RECORD
