Metadata-Version: 2.4
Name: bpe-openai
Version: 0.1.4
Classifier: Development Status :: 3 - Alpha
Classifier: Intended Audience :: Developers
Classifier: License :: OSI Approved :: MIT License
Classifier: Programming Language :: Python
Classifier: Programming Language :: Python :: 3
Classifier: Programming Language :: Python :: 3.9
Classifier: Programming Language :: Python :: 3.10
Classifier: Programming Language :: Python :: 3.11
Classifier: Programming Language :: Python :: 3.12
Classifier: Programming Language :: Rust
Classifier: Topic :: Software Development :: Libraries
Requires-Dist: typing-extensions>=4.8.0
Summary: Python bindings wrapping the bpe-openai Rust tokenizer crate with a tiktoken-compatible API.
Author-email: "Pathlit, Inc." <dev@pathlit.ai>
License: MIT
Requires-Python: >=3.9
Project-URL: Homepage, https://github.com/Pathlit-Inc/bpe-openai
Project-URL: Repository, https://github.com/Pathlit-Inc/bpe-openai
Project-URL: Documentation, https://github.com/Pathlit-Inc/bpe-openai#readme
